first_wheel/__init__.py
first_wheel/first_wheel.py
first_wheel-0.2.0.dist-info/LICENSE
first_wheel-0.2.0.dist-info/METADATA
first_wheel-0.2.0.dist-info/WHEEL
first_wheel-0.2.0.dist-info/entry_points.txt
first_wheel-0.2.0.dist-info/top_level.txt
first_wheel-0.2.0.dist-info/RECORD
