Metadata-Version: 2.1
Name: first-wheel
Version: 0.2.0
Summary: UNKNOWN
Home-page: UNKNOWN
Author: UNKNOWN
Author-email: UNKNOWN
License: UNKNOWN
Platform: UNKNOWN
Requires-Dist: docopt (>=0.6.2)
